paqueteoptimizacion_isabella/__init__.py
paqueteoptimizacion_isabella/FuncionesMultivariables/__init__.py
paqueteoptimizacion_isabella/FuncionesMultivariables/Directos/CaminataAleatoria.py
paqueteoptimizacion_isabella/FuncionesMultivariables/Directos/HookeJeeves.py
paqueteoptimizacion_isabella/FuncionesMultivariables/Directos/NelderMeadSimplex.py
paqueteoptimizacion_isabella/FuncionesMultivariables/Directos/__init__.py
paqueteoptimizacion_isabella/FuncionesMultivariables/Gradiente/Cauchy.py
paqueteoptimizacion_isabella/FuncionesMultivariables/Gradiente/FletcherReeves.py
paqueteoptimizacion_isabella/FuncionesMultivariables/Gradiente/Newton.py
paqueteoptimizacion_isabella/FuncionesMultivariables/Gradiente/__init__.py
paqueteoptimizacion_isabella/FuncionesPrueba/__init__.py
paqueteoptimizacion_isabella/FuncionesPrueba/Multivariables/__init__.py
paqueteoptimizacion_isabella/FuncionesPrueba/Multivariables/multi.py
paqueteoptimizacion_isabella/FuncionesPrueba/UnaVariable/__init__.py
paqueteoptimizacion_isabella/FuncionesPrueba/UnaVariable/solaVariable.py
paqueteoptimizacion_isabella/FuncionesUnaVariable/__init__.py
paqueteoptimizacion_isabella/FuncionesUnaVariable/BasadosEnLaDerivada/MetodoDeBiseccion.py
paqueteoptimizacion_isabella/FuncionesUnaVariable/BasadosEnLaDerivada/MetodoDeLaSecante.py
paqueteoptimizacion_isabella/FuncionesUnaVariable/BasadosEnLaDerivada/NewtonRaphson.py
paqueteoptimizacion_isabella/FuncionesUnaVariable/BasadosEnLaDerivada/__init__.py
paqueteoptimizacion_isabella/FuncionesUnaVariable/EliminacionDeRegiones/FibonacciSearch.py
paqueteoptimizacion_isabella/FuncionesUnaVariable/EliminacionDeRegiones/GoldenSectionSearch.py
paqueteoptimizacion_isabella/FuncionesUnaVariable/EliminacionDeRegiones/IntervalHalving.py
paqueteoptimizacion_isabella/FuncionesUnaVariable/EliminacionDeRegiones/__init__.py
paqueteoptimizacion_isabella-0.0.1.dist-info/METADATA
paqueteoptimizacion_isabella-0.0.1.dist-info/WHEEL
paqueteoptimizacion_isabella-0.0.1.dist-info/top_level.txt
paqueteoptimizacion_isabella-0.0.1.dist-info/RECORD
